{
    "number": 1024,
    "timestep_list": [
        {
            "number": 1,
            "state": {
                "two_finger_gripper": {
                    "pose": [
                        [
                            0.0,
                            0.0,
                            0.05
                        ],
                        [
                            0.0,
                            0.0,
                            0.0,
                            1.0
                        ]
                    ],
                    "joint_angles": {
                        "l_prox_pin": 0.75,
                        "l_distal_pin": -1.4,
                        "r_prox_pin": -0.75,
                        "r_distal_pin": 1.4
                    }
                },
                "obj_2": {
                    "pose": [
                        [
                            0.0,
                            0.16,
                            0.05
                        ],
                        [
                            0.0,
                            0.0,
                            0.0,
                            1.0
                        ]
                    ],
                    "velocity": [
                        [
                            0.0,
                            0.0,
                            0.0
                        ],
                        [
                            0.0,
                            0.0,
                            0.0
                        ]
                    ]
                }
            },
            "reward": {
                "distance_to_goal": 0.05499999999999999,
                "goal_position": [
                    0.0,
                    0.10500000000000001,
                    0
                ]
            },
            "action": {
                "target_joint_angles": [
                    0.5928565888642626,
                    -1.2429231339166584,
                    -0.5927287568614972,
                    1.2428751472226447
                ]
            }
        },
        {
            "number": 2,
            "state": {
                "two_finger_gripper": {
                    "pose": [
                        [
                            0.0,
                            0.0,
                            0.05
                        ],
                        [
                            0.0,
                            0.0,
                            0.0,
                            1.0
                        ]
                    ],
                    "joint_angles": {
                        "l_prox_pin": 0.7342856588864263,
                        "l_distal_pin": -1.38429183757874,
                        "r_prox_pin": -0.7342728756861497,
                        "r_distal_pin": 1.384286467996422
                    }
                },
                "obj_2": {
                    "pose": [
                        [
                            0.0,
                            0.16,
                            0.05
                        ],
                        [
                            0.0,
                            0.0,
                            0.0,
                            1.0
                        ]
                    ],
                    "velocity": [
                        [
                            0.0,
                            0.0,
                            0.0
                        ],
                        [
                            0.0,
                            0.0,
                            0.0
                        ]
                    ]
                }
            },
            "reward": {
                "distance_to_goal": 0.05572467082124948,
                "goal_position": [
                    0.0,
                    0.10500000000000001,
                    0
                ]
            },
            "action": {
                "target_joint_angles": [
                    0.5775165150497665,
                    -1.2271664918190441,
                    -0.5774426021056638,
                    1.227339494185526
                ]
            }
        },
        {
            "number": 3,
            "state": {
                "two_finger_gripper": {
                    "pose": [
                        [
                            0.0,
                            0.0,
                            0.05
                        ],
                        [
                            0.0,
                            0.0,
                            0.0,
                            1.0
                        ]
                    ],
                    "joint_angles": {
                        "l_prox_pin": 0.7189351670982636,
                        "l_distal_pin": -1.3656063485388619,
                        "r_prox_pin": -0.7189145967446162,
                        "r_distal_pin": 1.365628575005102
                    }
                },
                "obj_2": {
                    "pose": [
                        [
                            -1.587480570454908e-05,
                            0.1607246685600476,
                            0.05
                        ],
                        [
                            7.571918288983342e-19,
                            -1.8774763015768837e-17,
                            9.559735533535135e-05,
                            0.9999999954305728
                        ]
                    ],
                    "velocity": [
                        [
                            -0.0038099533690917793,
                            0.17392045441142512,
                            2.9753441426510883e-16
                        ],
                        [
                            3.6345207842478967e-16,
                            -9.011886261295425e-15,
                            0.04588673063086066
                        ]
                    ]
                }
            },
            "reward": {
                "distance_to_goal": 0.057148391581834934,
                "goal_position": [
                    0.0,
                    0.10500000000000001,
                    0
                ]
            },
            "action": {
                "target_joint_angles": [
                    0.5620045601041129,
                    -1.2086115095758332,
                    -0.5619198697433035,
                    1.2085330130181824
                ]
            }
        },
        {
            "number": 4,
            "state": {
                "two_finger_gripper": {
                    "pose": [
                        [
                            0.0,
                            0.0,
                            0.05
                        ],
                        [
                            0.0,
                            0.0,
                            0.0,
                            1.0
                        ]
                    ],
                    "joint_angles": {
                        "l_prox_pin": 0.7042105045936046,
                        "l_distal_pin": -1.3373728004378675,
                        "r_prox_pin": -0.7041783376341496,
                        "r_distal_pin": 1.3374041126668965
                    }
                },
                "obj_2": {
                    "pose": [
                        [
                            -6.31423767489583e-05,
                            0.16214835669930502,
                            0.05
                        ],
                        [
                            1.8775423455413262e-18,
                            -2.525905967590792e-17,
                            0.00010052565631289877,
                            0.9999999949472962
                        ]
                    ],
                    "velocity": [
                        [
                            -0.011344217050658212,
                            0.3416851534217772,
                            -6.822085477366944e-17
                        ],
                        [
                            5.38021375595087e-16,
                            -3.112412768991364e-15,
                            0.0023655844805989604
                        ]
                    ]
                }
            },
            "reward": {
                "distance_to_goal": 0.058558043640704445,
                "goal_position": [
                    0.0,
                    0.10500000000000001,
                    0
                ]
            },
            "action": {
                "target_joint_angles": [
                    0.547089990469432,
                    -1.1802905951246774,
                    -0.5470364474799251,
                    1.1801491632794776
                ]
            }
        },
        {
            "number": 5,
            "state": {
                "two_finger_gripper": {
                    "pose": [
                        [
                            0.0,
                            0.0,
                            0.05
                        ],
                        [
                            0.0,
                            0.0,
                            0.0,
                            1.0
                        ]
                    ],
                    "joint_angles": {
                        "l_prox_pin": 0.6894752915221957,
                        "l_distal_pin": -1.3090004515221365,
                        "r_prox_pin": -0.689435945972895,
                        "r_distal_pin": 1.3090348541656713
                    }
                },
                "obj_2": {
                    "pose": [
                        [
                            -0.00010614312897159743,
                            0.16355794744236532,
                            0.05
                        ],
                        [
                            2.953877485493412e-18,
                            -2.709689572237729e-17,
                            0.00011002771093168193,
                            0.9999999939469514
                        ]
                    ],
                    "velocity": [
                        [
                            -0.010320180533433393,
                            0.3383017783344699,
                            -2.615108409409614e-17
                        ],
                        [
                            5.166143390967243e-16,
                            -8.8211793777231025e-16,
                            0.004560986242308194
                        ]
                    ]
                }
            },
            "reward": {
                "distance_to_goal": 0.05994911570097944,
                "goal_position": [
                    0.0,
                    0.10500000000000001,
                    0
                ]
            },
            "action": {
                "target_joint_angles": [
                    0.5325241601777038,
                    -1.1519280505755094,
                    -0.5325390757842969,
                    1.1523130009409674
                ]
            }
        },
        {
            "number": 6,
            "state": {
                "two_finger_gripper": {
                    "pose": [
                        [
                            0.0,
                            0.0,
                            0.05
                        ],
                        [
                            0.0,
                            0.0,
                            0.0,
                            1.0
                        ]
                    ],
                    "joint_angles": {
                        "l_prox_pin": 0.674762244717701,
                        "l_distal_pin": -1.2805388492130951,
                        "r_prox_pin": -0.6747234265578038,
                        "r_distal_pin": 1.2806294087905008
                    }
                },
                "obj_2": {
                    "pose": [
                        [
                            -0.00014641526302968698,
                            0.16494893690383652,
                            0.05
                        ],
                        [
                            3.922863543893684e-18,
                            -1.945313971901012e-17,
                            8.649721684826123e-05,
                            0.9999999962591157
                        ]
                    ],
                    "velocity": [
                        [
                            -0.009665312173941492,
                            0.333837470753086,
                            4.408068224943155e-17
                        ],
                        [
                            4.650156595982425e-16,
                            3.669087428146382e-15,
                            -0.011294637214830254
                        ]
                    ]
                }
            },
            "reward": {
                "distance_to_goal": 0.061322476506416965,
                "goal_position": [
                    0.0,
                    0.10500000000000001,
                    0
                ]
            },
            "action": {
                "target_joint_angles": [
                    0.5179649365976504,
                    -1.1236574014522343,
                    -0.5177048210977369,
                    1.123559659606004
                ]
            }
        },
        {
            "number": 7,
            "state": {
                "two_finger_gripper": {
                    "pose": [
                        [
                            0.0,
                            0.0,
                            0.05
                        ],
                        [
                            0.0,
                            0.0,
                            0.0,
                            1.0
                        ]
                    ],
                    "joint_angles": {
                        "l_prox_pin": 0.6600690418628687,
                        "l_distal_pin": -1.2520126027358205,
                        "r_prox_pin": -0.6600034047006411,
                        "r_distal_pin": 1.2521081839938872
                    }
                },
                "obj_2": {
                    "pose": [
                        [
                            -0.00018344018191839354,
                            0.16632220213413507,
                            0.05
                        ],
                        [
                            4.821330774875974e-18,
                            -7.097522105724509e-18,
                            9.407073846630469e-05,
                            0.999999995575348
                        ]
                    ],
                    "velocity": [
                        [
                            -0.008885980533289577,
                            0.3295836552716491,
                            8.280061167890325e-17
                        ],
                        [
                            4.3068056400093116e-16,
                            5.9307194682741226e-15,
                            0.0036352903914855256
                        ]
                    ]
                }
            },
            "reward": {
                "distance_to_goal": 0.062677258760609,
                "goal_position": [
                    0.0,
                    0.10500000000000001,
                    0
                ]
            },
            "action": {
                "target_joint_angles": [
                    0.503018268482258,
                    -1.0952095191968867,
                    -0.5032344950616322,
                    1.0948416875073237
                ]
            }
        },
        {
            "number": 8,
            "state": {
                "two_finger_gripper": {
                    "pose": [
                        [
                            0.0,
                            0.0,
                            0.05
                        ],
                        [
                            0.0,
                            0.0,
                            0.0,
                            1.0
                        ]
                    ],
                    "joint_angles": {
                        "l_prox_pin": 0.6453544561997588,
                        "l_distal_pin": -1.2234162896131362,
                        "r_prox_pin": -0.6453124711928131,
                        "r_distal_pin": 1.2234904409594698
                    }
                },
                "obj_2": {
                    "pose": [
                        [
                            -0.00021377592510247038,
                            0.16767689419234322,
                            0.05
                        ],
                        [
                            5.871171689348073e-18,
                            -1.3258387362550125e-17,
                            0.00012238270781971116,
                            0.9999999925112364
                        ]
                    ],
                    "velocity": [
                        [
                            -0.007280578364178442,
                            0.325126093969954,
                            -4.671605888504089e-17
                        ],
                        [
                            5.041053777870137e-16,
                            -2.9572334372139077e-15,
                            0.013589745369677502
                        ]
                    ]
                }
            },
            "reward": {
                "distance_to_goal": 0.06401231087520462,
                "goal_position": [
                    0.0,
                    0.10500000000000001,
                    0
                ]
            },
            "action": {
                "target_joint_angles": [
                    0.48864879375997444,
                    -1.0662032426813515,
                    -0.4883103937411243,
                    1.066240851235461
                ]
            }
        },
        {
            "number": 9,
            "state": {
                "two_finger_gripper": {
                    "pose": [
                        [
                            0.0,
                            0.0,
                            0.05
                        ],
                        [
                            0.0,
                            0.0,
                            0.0,
                            1.0
                        ]
                    ],
                    "joint_angles": {
                        "l_prox_pin": 0.630676083498641,
                        "l_distal_pin": -1.1947303117835284,
                        "r_prox_pin": -0.6306000152313075,
                        "r_distal_pin": 1.1948249539000195
                    }
                },
                "obj_2": {
                    "pose": [
                        [
                            -0.00024548712997872653,
                            0.1690118401520598,
                            0.05
                        ],
                        [
                            6.8978485004761375e-18,
                            -1.694120797097422e-17,
                            0.00012024129600922947,
                            0.9999999927710154
                        ]
                    ],
                    "velocity": [
                        [
                            -0.007610689170301469,
                            0.32038703033198407,
                            -2.794881206812307e-17
                        ],
                        [
                            4.930348354276136e-16,
                            -1.7676875315127778e-15,
                            -0.0010278776765948495
                        ]
                    ]
                }
            },
            "reward": {
                "distance_to_goal": 0.06532679408057124,
                "goal_position": [
                    0.0,
                    0.10500000000000001,
                    0
                ]
            },
            "action": {
                "target_joint_angles": [
                    0.4737711197185759,
                    -1.037461592394379,
                    -0.473796094309442,
                    1.0380389821567344
                ]
            }
        },
        {
            "number": 10,
            "state": {
                "two_finger_gripper": {
                    "pose": [
                        [
                            0.0,
                            0.0,
                            0.05
                        ],
                        [
                            0.0,
                            0.0,
                            0.0,
                            1.0
                        ]
                    ],
                    "joint_angles": {
                        "l_prox_pin": 0.6159818185964829,
                        "l_distal_pin": -1.1659562230445766,
                        "r_prox_pin": -0.6159115844101698,
                        "r_distal_pin": 1.1661250608920912
                    }
                },
                "obj_2": {
                    "pose": [
                        [
                            -0.00027381598635664784,
                            0.17032622023086116,
                            0.05
                        ],
                        [
                            7.933775064652183e-18,
                            -2.2652010540429976e-17,
                            8.965996423708796e-05,
                            0.9999999959805453
                        ]
                    ],
                    "velocity": [
                        [
                            -0.006798925530701121,
                            0.31545121891232447,
                            -3.5460061732451894e-17
                        ],
                        [
                            4.97823020982691e-16,
                            -2.7410241447086715e-15,
                            -0.014679039332042067
                        ]
                    ]
                }
            },
            "reward": {
                "distance_to_goal": 0.06662264288051391,
                "goal_position": [
                    0.0,
                    0.10500000000000001,
                    0
                ]
            },
            "action": {
                "target_joint_angles": [
                    0.45882663311556726,
                    -1.0087691788332733,
                    -0.4586630664026929,
                    1.0092368201178843
                ]
            }
        },
        {
            "number": 11,
            "state": {
                "two_finger_gripper": {
                    "pose": [
                        [
                            0.0,
                            0.0,
                            0.05
                        ],
                        [
                            0.0,
                            0.0,
                            0.0,
                            1.0
                        ]
                    ],
                    "joint_angles": {
                        "l_prox_pin": 0.6012688551168796,
                        "l_distal_pin": -1.1370755254586231,
                        "r_prox_pin": -0.6011852054399853,
                        "r_distal_pin": 1.1373032577358404
                    }
                },
                "obj_2": {
                    "pose": [
                        [
                            -0.0003005765095571548,
                            0.17162196483252648,
                            0.05
                        ],
                        [
                            8.795745448071311e-18,
                            -5.831798974747222e-18,
                            6.815068867869835e-05,
                            0.9999999976777418
                        ]
                    ],
                    "velocity": [
                        [
                            -0.0064225255681216705,
                            0.3109787043996755,
                            7.72228326066959e-17
                        ],
                        [
                            4.1325575775595924e-16,
                            8.073820546466117e-15,
                            -0.01032445230036631
                        ]
                    ]
                }
            },
            "reward": {
                "distance_to_goal": 0.06790527112986805,
                "goal_position": [
                    0.0,
                    0.10500000000000001,
                    0
                ]
            },
            "action": {
                "target_joint_angles": [
                    0.44435933720743853,
                    -0.9802052942925402,
                    -0.444061614454603,
                    0.9800087597498052
                ]
            }
        },
        {
            "number": 12,
            "state": {
                "two_finger_gripper": {
                    "pose": [
                        [
                            0.0,
                            0.0,
                            0.05
                        ],
                        [
                            0.0,
                            0.0,
                            0.0,
                            1.0
                        ]
                    ],
                    "joint_angles": {
                        "l_prox_pin": 0.5866167521580472,
                        "l_distal_pin": -1.1080054331864193,
                        "r_prox_pin": -0.5865075092865737,
                        "r_distal_pin": 1.1082227771492756
                    }
                },
                "obj_2": {
                    "pose": [
                        [
                            -0.0003258544634493206,
                            0.17290448929260527,
                            0.05
                        ],
                        [
                            1.0032882463369033e-17,
                            -8.390906817560818e-18,
                            8.749466476597808e-05,
                            0.9999999961723418
                        ]
                    ],
                    "velocity": [
                        [
                            -0.00606670893411978,
                            0.3078058704189064,
                            -2.585496681307153e-17
                        ],
                        [
                            5.93855337852011e-16,
                            -1.228412965804568e-15,
                            0.009285108550156055
                        ]
                    ]
                }
            },
            "reward": {
                "distance_to_goal": 0.069165493846811,
                "goal_position": [
                    0.0,
                    0.10500000000000001,
                    0
                ]
            },
            "action": {
                "target_joint_angles": [
                    0.4295950885574331,
                    -0.951263183701212,
                    -0.42933751369997725,
                    0.9513734306901928
                ]
            }
        },
        {
            "number": 13,
            "state": {
                "two_finger_gripper": {
                    "pose": [
                        [
                            0.0,
                            0.0,
                            0.05
                        ],
                        [
                            0.0,
                            0.0,
                            0.0,
                            1.0
                        ]
                    ],
                    "joint_angles": {
                        "l_prox_pin": 0.571956695889966,
                        "l_distal_pin": -1.0788670387611403,
                        "r_prox_pin": -0.5718285568144142,
                        "r_distal_pin": 1.079106134231174
                    }
                },
                "obj_2": {
                    "pose": [
                        [
                            -0.0003494056545441661,
                            0.17416461128902427,
                            0.05
                        ],
                        [
                            1.1427385810050457e-17,
                            -1.7583276499610895e-17,
                            8.909040826921682e-05,
                            0.9999999960314495
                        ]
                    ],
                    "velocity": [
                        [
                            -0.005652285862762924,
                            0.30242927914056156,
                            -6.835835389300021e-17
                        ],
                        [
                            6.697412334367592e-16,
                            -4.412286550250456e-15,
                            0.0007659568845401997
                        ]
                    ]
                }
            },
            "reward": {
                "distance_to_goal": 0.07040089483398199,
                "goal_position": [
                    0.0,
                    0.10500000000000001,
                    0
                ]
            },
            "action": {
                "target_joint_angles": [
                    0.41514626461884463,
                    -0.9217600470375302,
                    -0.41499231326268327,
                    0.9219932918793068
                ]
            }
        },
        {
            "number": 14,
            "state": {
                "two_finger_gripper": {
                    "pose": [
                        [
                            0.0,
                            0.0,
                            0.05
                        ],
                        [
                            0.0,
                            0.0,
                            0.0,
                            1.0
                        ]
                    ],
                    "joint_angles": {
                        "l_prox_pin": 0.5573125817924739,
                        "l_distal_pin": -1.049718793932507,
                        "r_prox_pin": -0.5571779774086413,
                        "r_distal_pin": 1.0499909202025424
                    }
                },
                "obj_2": {
                    "pose": [
                        [
                            -0.00037016742099970745,
                            0.17539992165837845,
                            0.05
                        ],
                        [
                            1.2420494215659829e-17,
                            -9.554924720447263e-18,
                            8.597193152330032e-05,
                            0.9999999963044135
                        ]
                    ],
                    "velocity": [
                        [
                            -0.004982823949329925,
                            0.2964744886450003,
                            3.8194689363850034e-17
                        ],
                        [
                            4.763750315767994e-16,
                            3.853668415001063e-15,
                            -0.001496868843774798
                        ]
                    ]
                }
            },
            "reward": {
                "distance_to_goal": 0.07161323644001011,
                "goal_position": [
                    0.0,
                    0.10500000000000001,
                    0
                ]
            },
            "action": {
                "target_joint_angles": [
                    0.4003294953530224,
                    -0.8928886267157119,
                    -0.40026093177513566,
                    0.8927405208995443
                ]
            }
        },
        {
            "number": 15,
            "state": {
                "two_finger_gripper": {
                    "pose": [
                        [
                            0.0,
                            0.0,
                            0.05
                        ],
                        [
                            0.0,
                            0.0,
                            0.0,
                            1.0
                        ]
                    ],
                    "joint_angles": {
                        "l_prox_pin": 0.5426528303389585,
                        "l_distal_pin": -1.0205359210742637,
                        "r_prox_pin": -0.5425210950010106,
                        "r_distal_pin": 1.0208011681730562
                    }
                },
                "obj_2": {
                    "pose": [
                        [
                            -0.00038742400022817185,
                            0.1766121884601835,
                            0.05
                        ],
                        [
                            1.3603900876899285e-17,
                            -1.262342450083999e-17,
                            0.0001065036610606277,
                            0.9999999943284851
                        ]
                    ],
                    "velocity": [
                        [
                            -0.004141579014831457,
                            0.290944032433216,
                            -2.6550073446387708e-18
                        ],
                        [
                            5.680676674627776e-16,
                            -1.4729534700574935e-15,
                            0.009855230223728405
                        ]
                    ]
                }
            },
            "reward": {
                "distance_to_goal": 0.07280251373607426,
                "goal_position": [
                    0.0,
                    0.10500000000000001,
                    0
                ]
            },
            "action": {
                "target_joint_angles": [
                    0.38548304836867475,
                    -0.8636902535667983,
                    -0.38535167062590997,
                    0.8638175809379595
                ]
            }
        },
        {
            "number": 16,
            "state": {
                "two_finger_gripper": {
                    "pose": [
                        [
                            0.0,
                            0.0,
                            0.05
                        ],
                        [
                            0.0,
                            0.0,
                            0.0,
                            1.0
                        ]
                    ],
                    "joint_angles": {
                        "l_prox_pin": 0.5279771796177709,
                        "l_distal_pin": -0.9912743805412815,
                        "r_prox_pin": -0.5278418474316559,
                        "r_distal_pin": 0.9915611814142992
                    }
                },
                "obj_2": {
                    "pose": [
                        [
                            -0.0004041795427485892,
                            0.17780139178057316,
                            0.05
                        ],
                        [
                            1.446969327319458e-17,
                            1.3754202281375321e-17,
                            0.00011127754146539533,
                            0.9999999938086543
                        ]
                    ],
                    "velocity": [
                        [
                            -0.004021330204900159,
                            0.28540879689352133,
                            8.098057452092754e-17
                        ],
                        [
                            4.1420295452096793e-16,
                            1.2661273868551897e-14,
                            0.002291462607875768
                        ]
                    ]
                }
            },
            "reward": {
                "distance_to_goal": 0.07396651376080617,
                "goal_position": [
                    0.0,
                    0.10500000000000001,
                    0
                ]
            },
            "action": {
                "target_joint_angles": [
                    0.3706912152848399,
                    -0.8343201938811038,
                    -0.3709590834817373,
                    0.83429998671636
                ]
            }
        },
        {
            "number": 17,
            "state": {
                "two_finger_gripper": {
                    "pose": [
                        [
                            0.0,
                            0.0,
                            0.05
                        ],
                        [
                            0.0,
                            0.0,
                            0.0,
                            1.0
                        ]
                    ],
                    "joint_angles": {
                        "l_prox_pin": 0.513286941561861,
                        "l_distal_pin": -0.9620098854813911,
                        "r_prox_pin": -0.5131877359301978,
                        "r_distal_pin": 0.9622851593226842
                    }
                },
                "obj_2": {
                    "pose": [
                        [
                            -0.0004161481373846096,
                            0.17896534309158094,
                            0.04999999763513539
                        ],
                        [
                            -3.3345120540856785e-08,
                            -5.443096687227567e-08,
                            0.00013748276485393368,
                            0.9999999905492426
                        ]
                    ],
                    "velocity": [
                        [
                            -0.0028724627126448955,
                            0.27934831464186444,
                            -5.675675069026929e-07
                        ],
                        [
                            -1.6002750436087708e-05,
                            -2.61286450167815e-05,
                            0.012578507324155844
                        ]
                    ]
                }
            },
            "reward": {
                "distance_to_goal": 0.07510493569256377,
                "goal_position": [
                    0.0,
                    0.10500000000000001,
                    0
                ]
            },
            "action": {
                "target_joint_angles": [
                    0.356139700176515,
                    -0.8049336669286067,
                    -0.3562171370470352,
                    0.8053720389099543
                ]
            }
        },
        {
            "number": 18,
            "state": {
                "two_finger_gripper": {
                    "pose": [
                        [
                            0.0,
                            0.0,
                            0.05
                        ],
                        [
                            0.0,
                            0.0,
                            0.0,
                            1.0
                        ]
                    ],
                    "joint_angles": {
                        "l_prox_pin": 0.4986098921792301,
                        "l_distal_pin": -0.9327109883190802,
                        "r_prox_pin": -0.4985235779722444,
                        "r_distal_pin": 0.9330049339161107
                    }
                },
                "obj_2": {
                    "pose": [
                        [
                            -0.00042913640480876436,
                            0.18010370967755326,
                            0.04999999731644281
                        ],
                        [
                            -8.716079168271621e-08,
                            -5.620699473251019e-08,
                            0.00014596888362796134,
                            0.999999989346537
                        ]
                    ],
                    "velocity": [
                        [
                            -0.003117184181797152,
                            0.27320798063336077,
                            -7.648622032041935e-08
                        ],
                        [
                            -2.5831626436051216e-05,
                            -8.559089594607094e-07,
                            0.004073337051077057
                        ]
                    ]
                }
            },
            "reward": {
                "distance_to_goal": 0.07621741550050758,
                "goal_position": [
                    0.0,
                    0.10500000000000001,
                    0
                ]
            },
            "action": {
                "target_joint_angles": [
                    0.3414270125834814,
                    -0.7759030574531527,
                    -0.3416098949389745,
                    0.7760734571147955
                ]
            }
        },
        {
            "number": 19,
            "state": {
                "two_finger_gripper": {
                    "pose": [
                        [
                            0.0,
                            0.0,
                            0.05
                        ],
                        [
                            0.0,
                            0.0,
                            0.0,
                            1.0
                        ]
                    ],
                    "joint_angles": {
                        "l_prox_pin": 0.48392852842629897,
                        "l_distal_pin": -0.9034154337753898,
                        "r_prox_pin": -0.4838638617784535,
                        "r_distal_pin": 0.9036845776000345
                    }
                },
                "obj_2": {
                    "pose": [
                        [
                            -0.0004392025783448584,
                            0.18121615003837566,
                            0.04999999921589014
                        ],
                        [
                            -1.2464842373068568e-07,
                            -5.022027366481824e-09,
                            0.00017777682923150428,
                            0.9999999841976915
                        ]
                    ],
                    "velocity": [
                        [
                            -0.0024158816486625784,
                            0.26698568659737565,
                            4.558673608524868e-07
                        ],
                        [
                            -1.7998507845730895e-05,
                            2.4567488120583064e-05,
                            0.015267814087221417
                        ]
                    ]
                }
            },
            "reward": {
                "distance_to_goal": 0.07730303630676645,
                "goal_position": [
                    0.0,
                    0.10500000000000001,
                    0
                ]
            },
            "action": {
                "target_joint_angles": [
                    0.32694469142717425,
                    -0.7466833271781371,
                    -0.3270148803386411,
                    0.7464856348260589
                ]
            }
        },
        {
            "number": 20,
            "state": {
                "two_finger_gripper": {
                    "pose": [
                        [
                            0.0,
                            0.0,
                            0.05
                        ],
                        [
                            0.0,
                            0.0,
                            0.0,
                            1.0
                        ]
                    ],
                    "joint_angles": {
                        "l_prox_pin": 0.4692632696284139,
                        "l_distal_pin": -0.8741435713425337,
                        "r_prox_pin": -0.4692063361399455,
                        "r_distal_pin": 0.8743383584716525
                    }
                },
                "obj_2": {
                    "pose": [
                        [
                            -0.00044750409311967244,
                            0.18230174100453297,
                            0.050000003542059086
                        ],
                        [
                            -1.2231118901053475e-07,
                            1.020106827266697e-07,
                            0.0002324838145965106,
                            0.9999999729756249
                        ]
                    ],
                    "velocity": [
                        [
                            -0.0019923635459553665,
                            0.2605418318777596,
                            1.0382805458111178e-06
                        ],
                        [
                            1.112606692684042e-06,
                            5.1379172661356794e-05,
                            0.02625935352455609
                        ]
                    ]
                }
            },
            "reward": {
                "distance_to_goal": 0.07836352765003622,
                "goal_position": [
                    0.0,
                    0.10500000000000001,
                    0
                ]
            },
            "action": {
                "target_joint_angles": [
                    0.3121648309474193,
                    -0.7173089483562728,
                    -0.31201134815174086,
                    0.7171013764732619
                ]
            }
        },
        {
            "number": 21,
            "state": {
                "two_finger_gripper": {
                    "pose": [
                        [
                            0.0,
                            0.0,
                            0.05
                        ],
                        [
                            0.0,
                            0.0,
                            0.0,
                            1.0
                        ]
                    ],
                    "joint_angles": {
                        "l_prox_pin": 0.45458707153848416,
                        "l_distal_pin": -0.8448199351366138,
                        "r_prox_pin": -0.4545142421850522,
                        "r_distal_pin": 0.8449312941497675
                    }
                },
                "obj_2": {
                    "pose": [
                        [
                            -0.00045610392938588706,
                            0.18336220029429745,
                            0.04999998749369934
                        ],
                        [
                            -1.026366367834916e-06,
                            -1.952474469315699e-07,
                            0.00028772983852275787,
                            0.9999999586052234
                        ]
                    ],
                    "velocity": [
                        [
                            -0.0020639607038915038,
                            0.25451022954347113,
                            -3.851606338217268e-06
                        ],
                        [
                            -0.00043391059834654774,
                            -0.00014278153982407398,
                            0.02651809244680144
                        ]
                    ]
                }
            },
            "reward": {
                "distance_to_goal": 0.07939586113605468,
                "goal_position": [
                    0.0,
                    0.10500000000000001,
                    0
                ]
            },
            "action": {
                "target_joint_angles": [
                    0.2977732628308997,
                    -0.6876532498939795,
                    -0.29750270130573114,
                    0.6879520575364664
                ]
            }
        },
        {
            "number": 22,
            "state": {
                "two_finger_gripper": {
                    "pose": [
                        [
                            0.0,
                            0.0,
                            0.05
                        ],
                        [
                            0.0,
                            0.0,
                            0.0,
                            1.0
                        ]
                    ],
                    "joint_angles": {
                        "l_prox_pin": 0.43993421652031356,
                        "l_distal_pin": -0.8154944413549458,
                        "r_prox_pin": -0.4398349732279357,
                        "r_distal_pin": 0.8155670691115049
                    }
                },
                "obj_2": {
                    "pose": [
                        [
                            -0.00046565765124918914,
                            0.1843944955805345,
                            0.0499999745611233
                        ],
                        [
                            -1.6470889275055694e-06,
                            -4.397838950852768e-07,
                            0.0003195553616956923,
                            0.999999948940731
                        ]
                    ],
                    "velocity": [
                        [
                            -0.0022928932471924937,
                            0.24775086869688978,
                            -3.103818249210965e-06
                        ],
                        [
                            -0.00029791603076136845,
                            -0.00011744754034305784,
                            0.01527625189029653
                        ]
                    ]
                }
            },
            "reward": {
                "distance_to_goal": 0.0804000753566532,
                "goal_position": [
                    0.0,
                    0.10500000000000001,
                    0
                ]
            },
            "action": {
                "target_joint_angles": [
                    0.28316062478697923,
                    -0.6585964711453804,
                    -0.2831057546012967,
                    0.6583775306798706
                ]
            }
        },
        {
            "number": 23,
            "state": {
                "two_finger_gripper": {
                    "pose": [
                        [
                            0.0,
                            0.0,
                            0.05
                        ],
                        [
                            0.0,
                            0.0,
                            0.0,
                            1.0
                        ]
                    ],
                    "joint_angles": {
                        "l_prox_pin": 0.42528127382184644,
                        "l_distal_pin": -0.7862117245027538,
                        "r_prox_pin": -0.42517949701123725,
                        "r_distal_pin": 0.7861855490981818
                    }
                },
                "obj_2": {
                    "pose": [
                        [
                            -0.00047097056530127435,
                            0.18539869591033262,
                            0.049999962464658536
                        ],
                        [
                            -2.4179697447945134e-06,
                            -6.44923173073107e-07,
                            0.0003804294775829219,
                            0.9999999276335724
                        ]
                    ],
                    "velocity": [
                        [
                            -0.001275099372500449,
                            0.24100807915154493,
                            -2.9031515447711955e-06
                        ],
                        [
                            -0.00037000417516747146,
                            -9.853696849299136e-05,
                            0.029219577419675107
                        ]
                    ]
                }
            },
            "reward": {
                "distance_to_goal": 0.0813781830702645,
                "goal_position": [
                    0.0,
                    0.10500000000000001,
                    0
                ]
            },
            "action": {
                "target_joint_angles": [
                    0.2684530582949359,
                    -0.6289399233735354,
                    -0.2680015178884144,
                    0.6294082381809788
                ]
            }
        }
    ]
}